mkdocs_tccp_docs_styles/__init__.py
mkdocs_tccp_docs_styles/plugin.py
mkdocs_tccp_docs_styles/assets/logo360.svg
mkdocs_tccp_docs_styles/assets/trimble-logo.svg
mkdocs_tccp_docs_styles/styles/__init__.py
mkdocs_tccp_docs_styles/styles/admonition.css
mkdocs_tccp_docs_styles/styles/announcement.css
mkdocs_tccp_docs_styles/styles/colors.css
mkdocs_tccp_docs_styles/styles/modus-styles.css
mkdocs_tccp_docs_styles-0.2.10.dist-info/LICENSE
mkdocs_tccp_docs_styles-0.2.10.dist-info/METADATA
mkdocs_tccp_docs_styles-0.2.10.dist-info/WHEEL
mkdocs_tccp_docs_styles-0.2.10.dist-info/entry_points.txt
mkdocs_tccp_docs_styles-0.2.10.dist-info/top_level.txt
mkdocs_tccp_docs_styles-0.2.10.dist-info/RECORD
