Metadata-Version: 2.2
Name: mkdocs-tccp-docs-styles
Version: 0.2.10
Summary: MkDocs plugin for TCCP documentation styles
Author-email: Jeff Bendixsen <jeff_bendixsen@trimble.com>
License: MIT
Requires-Python: >=3.7
License-File: LICENSE
Requires-Dist: mkdocs>=1.0.0
